Workbook
Name aporte: APP!$D$17
Name patrimonio: APP!$D$20
Name qtd_anos: APP!$D$18
Name rendimento_carteira: APP!$D$13
Name salario: APP!$D$12
Name sugestao_investimento: APP!$D$14
Name taxa_mensal: APP!$D$19

Sheet APP
B11: CONFIGURAÇÕES
B12: Salário | D12: 2300
B13: Rendimento Carteira | D13: 0.006
B14: Sugestão de Investimento (30%) | D14: =D12*30% -> 690
B16: INVESTIMENTO MENSAL
B17: Quanto investir por mês ? | D17: 400
B18: Por Quantos Anos ? | D18: 5
B19: Taxa de Rendimento mensal ? | D19: 0.01079
B20: Patrimônio acumulado ? | D20: =FV(taxa_mensal,qtd_anos*12,aporte*-1) -> 33510.766
B21: Dividendos Mensais ? | D21: =patrimonio*rendimento_carteira -> 201.06459
B23: Cenários | D23: Dividendo
A24: 2 | B24: Quanto em 2 Anos ? | C24: =FV($D$19,$A24*12,$D$17*-1) -> 10891.051 | D24: =C24*rendimento_carteira -> 65.346306
A25: 5 | B25: Quanto em 5 Anos ? | C25: =FV($D$19,$A25*12,$D$17*-1) -> 33510.766 | D25: =C25*rendimento_carteira -> 201.06459
A26: 10 | B26: Quanto em 10 Anos ? | C26: =FV($D$19,$A26*12,$D$17*-1) -> 97313.685 | D26: =C26*rendimento_carteira -> 583.88211
A27: 20 | B27: Quanto em 20 Anos ? | C27: =FV($D$19,$A27*12,$D$17*-1) -> 450079.36 | D27: =C27*rendimento_carteira -> 2700.4762
A28: 30 | B28: Quanto em 30 Anos ? | C28: =FV($D$19,$A28*12,$D$17*-1) -> 1728867.9 | D28: =C28*rendimento_carteira -> 10373.207
B31: PERFIL | C31: Conservador
B32: VALOR A SER INVESTIDO POR MÊS | C32: =aporte -> 400
A34: VLR | B34: TIPO DE FII | C34: Percentual Sugerido | D34: Valores
A35: =D35 -> 120 | B35: PAPEL | C35: =VLOOKUP($C$31&"-"&B35,Planilha2!$A:$D,4,FALSE) -> 0.3 | D35: =C35*$C$32 -> 120
A36: =D36 -> 200 | B36: TIJOLO | C36: =VLOOKUP($C$31&"-"&B36,Planilha2!$A:$D,4,FALSE) -> 0.5 | D36: =C36*$C$32 -> 200
A37: =D37 -> 40 | B37: HÍBRIDOS | C37: =VLOOKUP($C$31&"-"&B37,Planilha2!$A:$D,4,FALSE) -> 0.1 | D37: =C37*$C$32 -> 40
A38: =D38 -> 40 | B38: FOFs | C38: =VLOOKUP($C$31&"-"&B38,Planilha2!$A:$D,4,FALSE) -> 0.1 | D38: =C38*$C$32 -> 40
A39: =D39 -> 0 | B39: DESENVOLVIMENTO | C39: =VLOOKUP($C$31&"-"&B39,Planilha2!$A:$D,4,FALSE) -> 0 | D39: =C39*$C$32 -> 0
A40: =D40 -> 0 | B40: HOTELARIAS | C40: =VLOOKUP($C$31&"-"&B40,Planilha2!$A:$D,4,FALSE) -> 0 | D40: =C40*$C$32 -> 0
D41: =SUM(D35:D40) -> 400
B58: RECOMENDAÇÃO
B60: Valor do investimento | C60: =aporte -> 400 | D60: =TEXT(aporte/D12,"0%") & " do salário" -> 17% do salário
B62: Melhor Investimento
B63: Perfil | C63: Tipo de FII | D63: Valor
B64: Conservador | C64: =_xlfn.XLOOKUP(D64,Planilha2!$E$3:$E$8,Planilha2!$C$3:$C$8,"0",0,1) -> TIJOLO | D64: =LARGE(Planilha2!$E$3:$E$8,1) -> 200
B65: Moderado | C65: =_xlfn.XLOOKUP(D65,Planilha2!$E$9:$E$14,Planilha2!$C$9:$C$14,"0",0,1) -> TIJOLO | D65: =LARGE(Planilha2!$E$9:$E$14,1) -> 140
B66: Agressivo | C66: =_xlfn.XLOOKUP(D66,Planilha2!$E$15:$E$20,Planilha2!$C$15:$C$20,"0",0,1) -> PAPEL | D66: =LARGE(Planilha2!$E$15:$E$20,1) -> 200

Sheet Planilha2
A2: CHAVE | B2: PERFIL | C2: TIPO DE FII | D2: % | E2: Valor
A3: =B3&"-"&C3 -> Conservador-PAPEL | B3: Conservador | C3: PAPEL | D3: 0.3 | E3: =D3*aporte -> 120 | H3: %
A4: =B4&"-"&C4 -> Conservador-TIJOLO | B4: Conservador | C4: TIJOLO | D4: 0.5 | E4: =D4*aporte -> 200 | G4: Moderado-TIJOLO | H4: =VLOOKUP(G4,$A:$D,4,FALSE) -> 0.35
A5: =B5&"-"&C5 -> Conservador-HÍBRIDOS | B5: Conservador | C5: HÍBRIDOS | D5: 0.1 | E5: =D5*aporte -> 40
A6: =B6&"-"&C6 -> Conservador-FOFs | B6: Conservador | C6: FOFs | D6: 0.1 | E6: =D6*aporte -> 40
A7: =B7&"-"&C7 -> Conservador-DESENVOLVIMENTO | B7: Conservador | C7: DESENVOLVIMENTO | D7: 0 | E7: =D7*aporte -> 0
A8: =B8&"-"&C8 -> Conservador-HOTELARIAS | B8: Conservador | C8: HOTELARIAS | D8: 0 | E8: =D8*aporte -> 0
A9: =B9&"-"&C9 -> Moderado-PAPEL | B9: Moderado | C9: PAPEL | D9: 0.32 | E9: =D9*aporte -> 128
A10: =B10&"-"&C10 -> Moderado-TIJOLO | B10: Moderado | C10: TIJOLO | D10: 0.35 | E10: =D10*aporte -> 140
A11: =B11&"-"&C11 -> Moderado-HÍBRIDOS | B11: Moderado | C11: HÍBRIDOS | D11: 0.1 | E11: =D11*aporte -> 40
A12: =B12&"-"&C12 -> Moderado-FOFs | B12: Moderado | C12: FOFs | D12: 0.05 | E12: =D12*aporte -> 20
A13: =B13&"-"&C13 -> Moderado-DESENVOLVIMENTO | B13: Moderado | C13: DESENVOLVIMENTO | D13: 0.1 | E13: =D13*aporte -> 40
A14: =B14&"-"&C14 -> Moderado-HOTELARIAS | B14: Moderado | C14: HOTELARIAS | D14: 0.1 | E14: =D14*aporte -> 40
A15: =B15&"-"&C15 -> Agressivo-PAPEL | B15: Agressivo | C15: PAPEL | D15: 0.5 | E15: =D15*aporte -> 200
A16: =B16&"-"&C16 -> Agressivo-TIJOLO | B16: Agressivo | C16: TIJOLO | D16: 0.1 | E16: =D16*aporte -> 40
... A20: =B20&"-"&C20 -> Agressivo-HOTELARIAS | B20: Agressivo | C20: HOTELARIAS | D20: 0.1 | E20: =D20*aporte -> 40
C64: =VLOOKUP(B64,Planilha2!$B$3:$E$20,2) -> #N/A | D64: {=_xlfn.XLOOKUP(M,Planilha2!$B:$B,Planilha2!$E:$E,"0",0,1)} -> #NAME?
